Workbook

Sheet READ ME
B2: INVISALIGN DOMINATION — ROI & GROWTH CALCULATOR
B4: HOW TO USE
B5: 1. Go to the ASSUMPTIONS sheet. Every cell shaded YELLOW is editable — these are your levers.
B6: 2. Everything else recalculates automatically: per-case profit, the marketing funnel, the 4 growth scenarios, the 30% margin solver and the sensitivity tables.
B7: 3. Start by entering your REAL numbers where you have them (current fee, current monthly case starts, current ad spend). Benchmarks are pre-filled where you don't.
B9: THE SHEETS
B10: • Assumptions ........ all editable inputs (pricing, COGS, clinical, marketing, overhead).
B11: • Per-Case Economics . profit & margin on a single case, by product and blended.
B12: • Marketing Funnel ... ad spend → leads → consults → started cases → revenue & ROAS.
B13: • Growth Scenarios ... full annual P&L across Current → Year 1 → Year 2 → Domination.
B14: • 30% Margin Solver .. shows exactly which levers get Invisalign to a 30%+ net margin (implant-level).
B15: • Sensitivity ........ how net margin moves with fee, CPA and associate split.
... B23: Built for: Kent & North London multi-site group | Currency: GBP | v1.0

Sheet Assumptions
B2: ASSUMPTIONS — edit YELLOW cells only
B4: 1 · PATIENT PRICING (£, your private fee)
B5: Comprehensive / Full fee | C5: 4500 | E5: UK £3,500–5,500+; London +20–30%. Kent suburban premium ~£4,000–4,750.
B6: Lite fee | C6: 2950 | E6: UK £2,500–3,800.
B7: i7 / Express fee | C7: 1800 | E7: UK £1,200–2,499.
B8: % of starts: Comprehensive | C8: 0.45 | E8: Product mix — must total 100% with the next two.
B9: % of starts: Lite | C9: 0.4
B10: % of starts: i7 / Express | C10: 0.15
B11: → Blended average fee | C11: =C5*C8+C6*C9+C7*C10 | E11: Auto-calculated weighted average fee per started case.
B13: 2 · COST OF GOODS (Align lab fees & consumables)
B14: Align lab fee — Comprehensive (list) | C14: 1300 | E14: ESTIMATE. Align global ASP ~$1,335 (VERIFIED). UK list ~£900–1,300.
B15: Align lab fee — Lite (list) | C15: 750 | E15: ESTIMATE ~£500–800.
B16: Align lab fee — i7 (list) | C16: 450 | E16: ESTIMATE ~£300–500.
B17: Tier discount on lab fee | C17: 0.3 | E17: Silver ~10% → Diamond ~38% → Apex ~46% (US-derived). YOUR LEVER.
B18: Vivera retainer cost to practice / case | C18: 200 | E18: £250–500/arch; allow 1 set. Often re-charged to patient.
B19: Other consumables / case (attachments, IPR, scans) | C19: 75 | E19: ESTIMATE.
B20: → Blended COGS per case (after tier discount) | C20: =(C14*C8+C15*C9+C16*C10)*(1-C17)+C18+C19 | E20: Weighted lab fee × (1 − tier discount) + retainer + consumables.
B22: 3 · CLINICAL DELIVERY
B23: Associate pay (% of fee AFTER lab fee) | C23: 0.45 | E23: UK 40–55% of gross after lab. Set to 0% if PRINCIPAL delivers (see note).
B24: Active chair hours per case | C24: 4 | E24: Consult+scan+fit+reviews+refinements ~3–5 hrs.
B25: Notional principal chair cost / hour | C25: 150 | E25: Used only when associate % = 0, to value owner time honestly.
B26: → Clinical cost per case | C26: =IF(C23>0,(C11-C20)*C23,C24*C25) | E26: Associate split of (fee−COGS), OR owner hours×rate if associate %=0.
B28: 4 · MARKETING FUNNEL (per channel blend)
B29: Cost per lead (blended Google+Meta) | C29: 60 | E29: Google £45–200; Meta £25–75. Blended ESTIMATE.
B30: Lead → consult booked | C30: 0.55 | E30: Speed-to-lead & TCO follow-up drive this.
B31: Consult booked → attended (show rate) | C31: 0.8 | E31: Deposit/reminders lift show rate.
B32: Consult attended → case STARTED | C32: 0.7 | E32: TCO benchmark 64–68% avg, 75%+ excellent (VERIFIED).
B33: % of starts from PAID (vs organic/referral) | C33: 0.6 | E33: Lower = cheaper blended CPA. Organic/referral assumed near-zero marginal cost.
B34: → Cost per STARTED case (paid only) | C34: =C29/(C30*C31*C32) | E34: CPL ÷ (book × show × close). This is the honest CPA, not a quoted number.
B35: → BLENDED marketing cost per started case | C35: =C34*C33 | E35: Paid CPA × paid share (organic/referral starts carry ~no marginal cost).
B37: 5 · OVERHEAD
B38: Variable admin / TCO / finance fees per case | C38: 175 | E38: TCO commission, 0% finance subsidy (~2–4% of fee), card fees, admin.
B39: Fixed overhead allocated to Invisalign / year | C39: 60000 | E39: Share of rent, reception, software, equipment. Spread over annual volume.
B41: KEY:
B42: Yellow = you edit
B43: Blue/Green = auto-calculated

Sheet Per-Case Economics
B2: PER-CASE ECONOMICS
B4: Line (per case) | C4: Comprehensive | D4: Lite | E4: i7/Express | F4: BLENDED
B5: Patient fee | C5: ='Assumptions'!C5 | D5: ='Assumptions'!C6 | E5: ='Assumptions'!C7 | F5: ='Assumptions'!C11
B6: Align lab fee (after tier discount) | C6: ='Assumptions'!C14*(1-'Assumptions'!C17) | D6: ='Assumptions'!C15*(1-'Assumptions'!C17) | E6: ='Assumptions'!C16*(1-'Assumptions'!C17) | F6: =(('Assumptions'!C14*'Assumptions'!C8+'Assumptions'!C15*'Assumptions'!C9+'Assumptions'!C16*'Assumptions'!C10))*(1-'Assumptions'!C17)
B7: Retainer + consumables | C7: ='Assumptions'!C18+'Assumptions'!C19 | D7: ='Assumptions'!C18+'Assumptions'!C19 | E7: ='Assumptions'!C18+'Assumptions'!C19 | F7: ='Assumptions'!C18+'Assumptions'!C19
B8: =Total COGS | C8: =C6+C7 | D8: =D6+D7 | E8: =E6+E7 | F8: =F6+F7
B9: Gross profit (fee − COGS) | C9: =C5-C8 | D9: =D5-D8 | E9: =E5-E8 | F9: =F5-F8
B10: Clinical delivery (associate split / owner time) | C10: =IF('Assumptions'!C23>0,(C5-C6)*'Assumptions'!C23,'Assumptions'!C24*'Assumptions'!C25) | D10: =IF('Assumptions'!C23>0,(D5-D6)*'Assumptions'!C23,'Assumptions'!C24*'Assumptions'!C25) | E10: =IF('Assumptions'!C23>0,(E5-E6)*'Assumptions'!C23,'Assumptions'!C24*'Assumptions'!C25) | F10: =IF('Assumptions'!C23>0,(F5-F6)*'Assumptions'!C23,'Assumptions'!C24*'Assumptions'!C25)
B11: Marketing (blended CPA) | C11: ='Assumptions'!C35 | D11: ='Assumptions'!C35 | E11: ='Assumptions'!C35 | F11: ='Assumptions'!C35
B12: Variable admin / TCO / finance | C12: ='Assumptions'!C38 | D12: ='Assumptions'!C38 | E12: ='Assumptions'!C38 | F12: ='Assumptions'!C38
B13: NET CONTRIBUTION per case (pre-fixed-OH) | C13: =C9-C10-C11-C12 | D13: =D9-D10-D11-D12 | E13: =E9-E10-E11-E12 | F13: =F9-F10-F11-F12
B14: Contribution margin % | C14: =C13/C5 | D14: =D13/D5 | E14: =E13/E5 | F14: =F13/F5
B16: Note: 'Contribution margin' excludes fixed overhead. True NET margin after fixed overhead is on the Growth Scenarios sheet (depends on volume). Target = 30%+.

Sheet Marketing Funnel
B2: MARKETING FUNNEL — what does my ad spend buy?
B4: EDIT: Monthly paid ad spend (£) | C4: 8000
B5: Leads generated / month | C5: =C4/'Assumptions'!C29 | D5: spend ÷ cost-per-lead
B6: Consults booked / month | C6: =C5*'Assumptions'!C30 | D6: × lead→book rate
B7: Consults attended / month | C7: =C6*'Assumptions'!C31 | D7: × show rate
B8: Cases STARTED from paid / month | C8: =C7*'Assumptions'!C32 | D8: × consult→start rate
B9: Cost per started case (paid) | C9: =C4/C8 | D9: the honest paid CPA
B10: Revenue from these starts / month | C10: =C8*'Assumptions'!C11 | D10: × blended fee
B11: Net contribution from these starts / month | C11: =C8*'Per-Case Economics'!F13 | D11: × per-case net contribution
B12: ROAS (revenue ÷ spend) | C12: =C10/C4 | D12: gross return on ad spend
B13: Return on marketing £ (contribution ÷ spend) | C13: =C11/C4 | D13: profit return on ad spend
B14: Annual starts from paid | C14: =C8*12
B15: Annual revenue from paid | C15: =C10*12

Sheet Growth Scenarios
B2: GROWTH SCENARIOS — annual P&L (Invisalign only)
C4: CURRENT | D4: YEAR 1 | E4: YEAR 2 | F4: DOMINATION
B5: Cases STARTED per month (EDIT) | C5: 10 | D5: 20 | E5: 35 | F5: 60
B6: Cases STARTED per year | C6: =C5*12 | D6: =D5*12 | E6: =E5*12 | F6: =F5*12
B7: → Implied Invisalign tier (annual) | C7: =IF(C6>=400,"Diamond Apex",IF(C6>=200,"Diamond",IF(C6>=140,"Platinum Elite",IF(C6>=110,"Platinum",IF(C6>=30,"Gold","Silver/Bronze"))))) | D7: =IF(D6>=400,"Diamond Apex",IF(D6>=200,"Diamond",IF(D6>=140,"Platinum Elite",IF(D6>=110,"Platinum",IF(D6>=30,"Gold","Silver/Bronze"))))) | E7: =IF(E6>=400,"Diamond Apex",IF(E6>=200,"Diamond",IF(E6>=140,"Platinum Elite",IF(E6>=110,"Platinum",IF(E6>=30,"Gold","Silver/Bronze"))))) | F7: =IF(F6>=400,"Diamond Apex",IF(F6>=200,"Diamond",IF(F6>=140,"Platinum Elite",IF(F6>=110,"Platinum",IF(F6>=30,"Gold","Silver/Bronze")))))
B8: Revenue | C8: =C6*'Assumptions'!C11 | D8: =D6*'Assumptions'!C11 | E8: =E6*'Assumptions'!C11 | F8: =F6*'Assumptions'!C11
B9: − COGS (lab+retainer+consumables) | C9: =-C6*'Per-Case Economics'!F8 | D9: =-D6*'Per-Case Economics'!F8 | E9: =-E6*'Per-Case Economics'!F8 | F9: =-F6*'Per-Case Economics'!F8
B10: − Clinical delivery | C10: =-C6*'Per-Case Economics'!F10 | D10: =-D6*'Per-Case Economics'!F10 | E10: =-E6*'Per-Case Economics'!F10 | F10: =-F6*'Per-Case Economics'!F10
B11: − Marketing | C11: =-C6*'Per-Case Economics'!F11 | D11: =-D6*'Per-Case Economics'!F11 | E11: =-E6*'Per-Case Economics'!F11 | F11: =-F6*'Per-Case Economics'!F11
B12: − Variable admin/TCO/finance | C12: =-C6*'Per-Case Economics'!F12 | D12: =-D6*'Per-Case Economics'!F12 | E12: =-E6*'Per-Case Economics'!F12 | F12: =-F6*'Per-Case Economics'!F12
B13: − Fixed overhead allocation | C13: =-'Assumptions'!C39 | D13: =-'Assumptions'!C39 | E13: =-'Assumptions'!C39 | F13: =-'Assumptions'!C39
B14: =NET PROFIT (Invisalign) | C14: =SUM(C8:C13) | D14: =SUM(D8:D13) | E14: =SUM(E8:E13) | F14: =SUM(F8:F13)
B15: NET MARGIN % | C15: =C14/C8 | D15: =D14/D8 | E15: =E14/E8 | F15: =F14/F8
B16: Profit per working day (240/yr) | C16: =C14/240 | D16: =D14/240 | E16: =E14/240 | F16: =F14/240
B18: Targets: Domination = Diamond Apex (≥400/yr). The 30% margin line is the implant-equivalent benchmark — watch the NET MARGIN row turn ≥30% as volume dilutes fixed overhead and tier discount cuts COGS.

Sheet 30% Margin Solver
B2: CAN INVISALIGN HIT A 30% NET MARGIN? — lever solver
B4: Three stages: a typical mid-tier setup, then the same practice at Diamond/Apex scale, then the premium-optimised model. Each column shows net margin per case AFTER a fair share of fixed overhead.
B5: Lever (per case) | C5: STAGE 1 Mid-tier | D5: STAGE 2 Diamond scale | E5: STAGE 3 Apex optimised | F5: What changed
B6: Blended fee (£) | C6: 3400 | D6: 3800 | E6: 4100 | F6: Hold/raise price with stronger brand & before/afters
B7: Blended lab fee — list (£) | C7: 1000 | D7: 1000 | E7: 1000 | F7: Same Align list price
B8: Tier discount on lab | C8: 0.1 | D8: 0.38 | E8: 0.46 | F8: Silver→Diamond→Apex unlocks bigger COGS cuts
B9: Retainer + consumables (£) | C9: 275 | D9: 250 | E9: 225 | F9: Buying power + efficiency
B10: Associate split of (fee−lab) | C10: 0.45 | D10: 0.45 | E10: 0.4 | F10: Productivity bonuses tied to volume, not flat %
B11: Blended marketing CPA (£) | C11: 400 | D11: 250 | E11: 170 | F11: Organic/referral/brand reduce paid dependence
B12: Admin/TCO/finance (£) | C12: 200 | D12: 175 | E12: 150 | F12: Process & scale efficiency
B13: Fixed overhead / case (£) | C13: 450 | D13: 220 | E13: 150 | F13: Volume dilutes fixed cost (more cases, same rent)
B14: Lab fee after discount (£) | C14: =C7*(1-C8) | D14: =D7*(1-D8) | E14: =E7*(1-E8)
B15: Total COGS (£) | C15: =C14+C9 | D15: =D14+D9 | E15: =E14+E9
B16: Clinical delivery (£) | C16: =(C6-C14)*C10 | D16: =(D6-D14)*D10 | E16: =(E6-E14)*E10
B17: NET PROFIT per case (£) | C17: =C6-C15-C16-C11-C12-C13 | D17: =D6-D15-D16-D11-D12-D13 | E17: =E6-E15-E16-E11-E12-E13
B18: NET MARGIN % | C18: =C17/C6 | D18: =D17/D6 | E18: =E17/E6
B19: vs 30% target | C19: =IF(C18>=0.3,"✓ HITS 30%","✗ below") | D19: =IF(D18>=0.3,"✓ HITS 30%","✗ below") | E19: =IF(E18>=0.3,"✓ HITS 30%","✗ below")
B21: VERDICT (computed): Stage 1 (mid-tier, paid-dependent, full overhead drag, 45% associate split) lands ~1–15% net — well below implants. Stage 2 (Diamond volume: COGS discount up, overhead/case down, CPA controlled, still 45% split) reaches ~20–25% — good, but the ASSOCIATE SPLIT is the ceiling. Stage 3 (Apex: premium fee, ~46% lab discount, lean £170 CPA, volume-diluted overhead AND split trimmed to 40% with productivity bonuses) clears ~35%. BOTTOM LINE: 30%+ IS achievable, but it is the combined payoff of SCALE + EFFICIENCY + the delivery model. The single biggest lever is clinical delivery cost: an associate at 45% caps you near 25%; an owner-leveraged or low-split/TCO-heavy model (set associate % lower on the Assumptions sheet) pushes 35–45%. Getting to Diamond/Apex is therefore BOTH the volume strategy and the margin strategy.

Sheet Sensitivity
B2: SENSITIVITY — net contribution margin %
B4: Margin % by FEE (rows) × BLENDED CPA (cols). Uses current COGS, associate % & admin from Assumptions.
B6: Fee ↓ / CPA → | C6: 150 | D6: 250 | E6: 350 | F6: 450 | G6: 550
B7: 3000 | C7: =(3000-'Assumptions'!C20-(3000-('Assumptions'!C20-'Assumptions'!C18-'Assumptions'!C19))*'Assumptions'!C23-150-'Assumptions'!C38)/3000 | D7: =(3000-'Assumptions'!C20-(3000-('Assumptions'!C20-'Assumptions'!C18-'Assumptions'!C19))*'Assumptions'!C23-250-'Assumptions'!C38)/3000 | E7: =(3000-'Assumptions'!C20-(3000-('Assumptions'!C20-'Assumptions'!C18-'Assumptions'!C19))*'Assumptions'!C23-350-'Assumptions'!C38)/3000 | F7: =(3000-'Assumptions'!C20-(3000-('Assumptions'!C20-'Assumptions'!C18-'Assumptions'!C19))*'Assumptions'!C23-450-'Assumptions'!C38)/3000 | G7: =(3000-'Assumptions'!C20-(3000-('Assumptions'!C20-'Assumptions'!C18-'Assumptions'!C19))*'Assumptions'!C23-550-'Assumptions'!C38)/3000
B8: 3400 | C8: =(3400-'Assumptions'!C20-(3400-('Assumptions'!C20-'Assumptions'!C18-'Assumptions'!C19))*'Assumptions'!C23-150-'Assumptions'!C38)/3400 | D8: =(3400-'Assumptions'!C20-(3400-('Assumptions'!C20-'Assumptions'!C18-'Assumptions'!C19))*'Assumptions'!C23-250-'Assumptions'!C38)/3400 | E8: =(3400-'Assumptions'!C20-(3400-('Assumptions'!C20-'Assumptions'!C18-'Assumptions'!C19))*'Assumptions'!C23-350-'Assumptions'!C38)/3400 | F8: =(3400-'Assumptions'!C20-(3400-('Assumptions'!C20-'Assumptions'!C18-'Assumptions'!C19))*'Assumptions'!C23-450-'Assumptions'!C38)/3400 | G8: =(3400-'Assumptions'!C20-(3400-('Assumptions'!C20-'Assumptions'!C18-'Assumptions'!C19))*'Assumptions'!C23-550-'Assumptions'!C38)/3400
B9: 3800 | C9: =(3800-'Assumptions'!C20-(3800-('Assumptions'!C20-'Assumptions'!C18-'Assumptions'!C19))*'Assumptions'!C23-150-'Assumptions'!C38)/3800 | D9: =(3800-'Assumptions'!C20-(3800-('Assumptions'!C20-'Assumptions'!C18-'Assumptions'!C19))*'Assumptions'!C23-250-'Assumptions'!C38)/3800 | E9: =(3800-'Assumptions'!C20-(3800-('Assumptions'!C20-'Assumptions'!C18-'Assumptions'!C19))*'Assumptions'!C23-350-'Assumptions'!C38)/3800 | F9: =(3800-'Assumptions'!C20-(3800-('Assumptions'!C20-'Assumptions'!C18-'Assumptions'!C19))*'Assumptions'!C23-450-'Assumptions'!C38)/3800 | G9: =(3800-'Assumptions'!C20-(3800-('Assumptions'!C20-'Assumptions'!C18-'Assumptions'!C19))*'Assumptions'!C23-550-'Assumptions'!C38)/3800
B10: 4200 | C10: =(4200-'Assumptions'!C20-(4200-('Assumptions'!C20-'Assumptions'!C18-'Assumptions'!C19))*'Assumptions'!C23-150-'Assumptions'!C38)/4200 | D10: =(4200-'Assumptions'!C20-(4200-('Assumptions'!C20-'Assumptions'!C18-'Assumptions'!C19))*'Assumptions'!C23-250-'Assumptions'!C38)/4200 | E10: =(4200-'Assumptions'!C20-(4200-('Assumptions'!C20-'Assumptions'!C18-'Assumptions'!C19))*'Assumptions'!C23-350-'Assumptions'!C38)/4200 | F10: =(4200-'Assumptions'!C20-(4200-('Assumptions'!C20-'Assumptions'!C18-'Assumptions'!C19))*'Assumptions'!C23-450-'Assumptions'!C38)/4200 | G10: =(4200-'Assumptions'!C20-(4200-('Assumptions'!C20-'Assumptions'!C18-'Assumptions'!C19))*'Assumptions'!C23-550-'Assumptions'!C38)/4200
B11: 4600 | C11: =(4600-'Assumptions'!C20-(4600-('Assumptions'!C20-'Assumptions'!C18-'Assumptions'!C19))*'Assumptions'!C23-150-'Assumptions'!C38)/4600 | D11: =(4600-'Assumptions'!C20-(4600-('Assumptions'!C20-'Assumptions'!C18-'Assumptions'!C19))*'Assumptions'!C23-250-'Assumptions'!C38)/4600 | E11: =(4600-'Assumptions'!C20-(4600-('Assumptions'!C20-'Assumptions'!C18-'Assumptions'!C19))*'Assumptions'!C23-350-'Assumptions'!C38)/4600 | F11: =(4600-'Assumptions'!C20-(4600-('Assumptions'!C20-'Assumptions'!C18-'Assumptions'!C19))*'Assumptions'!C23-450-'Assumptions'!C38)/4600 | G11: =(4600-'Assumptions'!C20-(4600-('Assumptions'!C20-'Assumptions'!C18-'Assumptions'!C19))*'Assumptions'!C23-550-'Assumptions'!C38)/4600
B13: Green ≈ at/above 30% (implant-equivalent). Red = thin. Conditional shading is approximate; use Growth Scenarios for the true after-fixed-overhead net margin.
